{
    "accession": "ENCBS459ENC", 
    "age": "57", 
    "age_units": "year", 
    "biosample_term_id": "CL:0002540", 
    "biosample_term_name": "mesenchymal stem cell of the bone marrow", 
    "biosample_type": "stem cell", 
    "characterizations": [], 
    "dbxrefs": [
        "GEO:SAMN06044719", 
        "Cellosaurus:CVCL_Y510", 
        "UCSC-ENCODE-cv:hMSC-BM", 
        "UCSC-ENCODE-cv:hMSC-BM_0050602.11"
    ], 
    "description": "Mesenchymal Stem Cells from femoral head bone marrow (hMSC-BM) that were surgically ressected from a 57 year old caucasian male", 
    "documents": [
        {
            "attachment": "/documents/98b5828b-7ac7-442e-9773-661504622f35/@@download/attachment/hMSCBM0050602.11_Gingeras_protocol.pdf", 
            "document_type": "certificate of analysis", 
            "references": [], 
            "urls": []
        }
    ], 
    "donor": "ENCDO134AAA", 
    "health_status": "negative for Bac/Fung/Myc, negative for HIV-1/HBV/HCV", 
    "lab": "Thomas Gingeras, CSHL", 
    "life_stage": "adult", 
    "organism": "Homo sapiens", 
    "passage_number": 2, 
    "references": [], 
    "sex": "male", 
    "source": "PromoCell", 
    "summary": "Homo sapiens mesenchymal of the bone marrow stem cell male adult (57 years)", 
    "treatments": [], 
    "url": "http://www.promocell.com/products/human-stem-and-blood-cells/mesenchymal-stem-cells/human-mesenchymal-stem-cells-from-bone-marrow-hmsc-bm"
}