{
    "accession": "ENCBS878QCW",
    "age": "62",
    "age_units": "year",
    "applied_modifications": [],
    "biosample_term_id": "UBERON:0002084",
    "biosample_term_name": "heart left ventricle",
    "biosample_type": "tissue",
    "characterizations": [],
    "dbxrefs": [
        "GEO:SAMN31998674"
    ],
    "description": "Homo sapiens heart left ventricle tissue",
    "documents": [
        {
            "attachment": "/documents/c4b8952c-d9f1-42e7-8ea5-54659d14f46b/@@download/attachment/ENCODE4_Snyder_HumanTissuePreservation_Flash_v1.pdf",
            "document_type": "general protocol",
            "references": [],
            "urls": []
        }
    ],
    "donor": "ENCDO110LFV",
    "health_status": "familial (EF 27%, LVEDD 6.5, LVPWd 0.85)",
    "lab": "Michael Snyder, Stanford",
    "life_stage": "adult",
    "organism": "Homo sapiens",
    "references": [],
    "sex": "male",
    "source": "Shin Lin",
    "subcellular_fraction_term_name": "nucleus",
    "summary": "Homo sapiens male adult (62 years) heart left ventricle tissue, preserved by flash-freezing nuclear fraction",
    "treatments": []
}