{
    "accession": "ENCBS669DHV",
    "age": "unknown",
    "applied_modifications": [],
    "biosample_term_id": "CLO:0024937",
    "biosample_term_name": "GM18498",
    "biosample_type": "cell line",
    "characterizations": [],
    "dbxrefs": [],
    "description": "GM18498 LCLs; Donor from the Yoruba in Ibadan, Nigeria (YRI)",
    "documents": [],
    "donor": "ENCDO740YRZ",
    "lab": "Stephen Montgomery, Stanford",
    "life_stage": "adult",
    "organism": "Homo sapiens",
    "references": [],
    "sex": "male",
    "source": "Coriell",
    "summary": "Homo sapiens GM18498 cell line",
    "treatments": []
}