{
    "accession": "ENCBS273GCM",
    "age": "62.5",
    "age_units": "hour",
    "applied_modifications": [
        {
            "category": "insertion",
            "introduced_tags": [
                {
                    "location": "C-terminal",
                    "name": "eGFP"
                },
                {
                    "location": "C-terminal",
                    "name": "3xFLAG"
                }
            ],
            "method": "CRISPR",
            "modified_site_by_target_id": "ceh-91",
            "purpose": "tagging"
        }
    ],
    "biosample_term_id": "UBERON:0000468",
    "biosample_term_name": "whole organism",
    "biosample_type": "whole organisms",
    "characterizations": [
        {
            "references": []
        }
    ],
    "dbxrefs": [],
    "description": "",
    "documents": [],
    "donor": "ENCDO413ARG",
    "lab": "Valerie Reinke, Yale",
    "life_stage": "young adult",
    "organism": "Caenorhabditis elegans",
    "references": [],
    "sex": "unknown",
    "source": "Valerie Reinke",
    "summary": "Caenorhabditis elegans strain RW12305 (st12305[ceh-91::TY1::EGFP::3xFLAG] III) young adult (62.5 hours) at L1 larva starved after bleaching stage whole organism genetically modified (insertion) using CRISPR targeting C. elegans ceh-91",
    "treatments": [],
    "worm_synchronization_stage": "L1 larva starved after bleaching"
}