{
    "accession": "ENCBS974GPH", 
    "age": "12.5", 
    "age_units": "day", 
    "applied_modifications": [], 
    "biosample_term_id": "UBERON:0001890", 
    "biosample_term_name": "forebrain", 
    "biosample_type": "tissue", 
    "characterizations": [], 
    "dbxrefs": [
        "GEO:SAMN05202059"
    ], 
    "description": "Forebrain from 120 embryonic 12.5 day mice", 
    "documents": [
        {
            "attachment": "/documents/631aa21c-8e48-467e-8cac-d40c875b3913/@@download/attachment/StandardTissueExcisionProtocol_02132017.pdf", 
            "document_type": "excision protocol", 
            "references": [], 
            "urls": []
        }
    ], 
    "donor": "ENCDO956IXV", 
    "health_status": "healthy", 
    "lab": "Len Pennacchio, LBNL", 
    "life_stage": "embryonic", 
    "organism": "Mus musculus", 
    "references": [], 
    "sex": "mixed", 
    "source": "Len Pennacchio", 
    "summary": "Mus musculus strain B6NCrl forebrain tissue mixed sex embryo (12.5 days)", 
    "treatments": []
}