{
    "accession": "ENCBS322FGS", 
    "age": "unknown", 
    "biosample_term_id": "EFO:0005903", 
    "biosample_term_name": "KBM-7", 
    "biosample_type": "immortalized cell line", 
    "characterizations": [], 
    "dbxrefs": [
        "GEO:SAMN06044783", 
        "Cellosaurus:CVCL_A426"
    ], 
    "description": "", 
    "documents": [
        {
            "attachment": "/documents/0a78e89a-9a5c-4523-abb7-0245994f26f3/@@download/attachment/KBM7_haploid_CML_SOP_V1.pdf", 
            "document_type": "growth protocol", 
            "references": [], 
            "urls": []
        }
    ], 
    "donor": "ENCDO763VKT", 
    "lab": "John Stamatoyannopoulos, UW", 
    "life_stage": "unknown", 
    "organism": "Homo sapiens", 
    "references": [], 
    "sex": "unknown", 
    "source": "Haplogen Genomics", 
    "summary": "Homo sapiens KBM-7 immortalized cell line", 
    "treatments": []
}