{
    "accession": "ENCBS838OKI",
    "age": "14",
    "age_units": "day",
    "applied_modifications": [],
    "biosample_term_id": "UBERON:0001388",
    "biosample_term_name": "gastrocnemius",
    "biosample_type": "tissue",
    "characterizations": [],
    "dbxrefs": [
        "GEO:SAMN22819058"
    ],
    "description": "B6Cast F1 PND14 Female 04 gastrocnemius for Wold core",
    "documents": [],
    "donor": "ENCDO509HIY",
    "lab": "Barbara Wold, Caltech",
    "life_stage": "postnatal",
    "organism": "Mus musculus",
    "references": [],
    "sex": "female",
    "source": "The Jackson Laboratory",
    "summary": "Mus musculus strain B6CASTF1/J female postnatal (14 days) gastrocnemius tissue",
    "treatments": []
}