{
    "accession": "ENCBS612ENC", 
    "age": "unknown", 
    "award": "U54HG004557", 
    "biosample_term_id": "CL:0002553", 
    "biosample_term_name": "fibroblast of lung", 
    "biosample_type": "primary cell", 
    "characterizations": [], 
    "dbxrefs": [
        "UCSC-ENCODE-cv:NHLF"
    ], 
    "description": "lung fibroblasts", 
    "donor": "ENCDO269AAA", 
    "health_status": "unknown", 
    "lab": "Thomas Gingeras, CSHL", 
    "life_stage": "unknown", 
    "lot_id": "Unknown", 
    "organism": "Homo sapiens", 
    "product_id": "Unknown", 
    "protocol_documents": [], 
    "references": [], 
    "sex": "unknown", 
    "source": "Unknown Source", 
    "treatments": []
}