{
    "accession": "ENCBS154EVO",
    "age": "8-10",
    "age_units": "month",
    "applied_modifications": [],
    "biosample_term_id": "NTR:0000646",
    "biosample_term_name": "left cerebral cortex",
    "biosample_type": "tissue",
    "characterizations": [],
    "dbxrefs": [],
    "description": "B6 X Cast L. cortex (brain)_8-10 months male animal 2_ENC4_cDNA_836",
    "documents": [],
    "donor": "ENCDO509HIY",
    "lab": "Barbara Wold, Caltech",
    "life_stage": "adult",
    "organism": "Mus musculus",
    "references": [],
    "sex": "male",
    "source": "The Jackson Laboratory",
    "summary": "Mus musculus strain B6CASTF1/J male adult (8-10 months) left cerebral cortex tissue",
    "treatments": []
}