{
    "accession": "ENCBS168FVU",
    "age": "83",
    "age_units": "year",
    "applied_modifications": [],
    "biosample_term_id": "UBERON:0006483",
    "biosample_term_name": "middle frontal area 46",
    "biosample_type": "tissue",
    "characterizations": [],
    "dbxrefs": [],
    "description": "human_brain_Rush ID_E1488495_BS121_ENC4_cDNA683",
    "documents": [],
    "donor": "ENCDO448ZXP",
    "lab": "Barbara Wold, Caltech",
    "life_stage": "adult",
    "organism": "Homo sapiens",
    "references": [],
    "sex": "female",
    "source": "Rush University",
    "summary": "Homo sapiens female adult (83 years) middle frontal area 46 tissue",
    "treatments": []
}