{
    "accession": "ENCBS475ENC", 
    "age": "55", 
    "age_units": "year", 
    "biosample_term_id": "CL:0002551", 
    "biosample_term_name": "fibroblast of dermis", 
    "biosample_type": "primary cell", 
    "characterizations": [], 
    "dbxrefs": [
        "UCSC-ENCODE-cv:NHDF", 
        "UCSC-ENCODE-cv:NHDF_0060801.3", 
        "GEO:SAMN04284387"
    ], 
    "description": "Skin Fibroblasts (NHDF) from the temple dermal layer that were surgically resected from a 55 year old caucasian female.", 
    "donor": "ENCDO119AAA", 
    "health_status": "negative for Bac/Fung/Myc, negative for HIV-1/HBV/HCV", 
    "lab": "Thomas Gingeras, CSHL", 
    "life_stage": "adult", 
    "organism": "Homo sapiens", 
    "passage_number": 2, 
    "protocol_documents": [
        {
            "attachment": "/documents/6f46cc38-2a6e-4bba-a542-05dcf52c7da8/@@download/attachment/NHDF0060801.3_Gingeras_protocol.pdf", 
            "references": [], 
            "urls": []
        }
    ], 
    "references": [], 
    "sex": "female", 
    "source": "PromoCell", 
    "summary": "Homo sapiens  fibroblast of dermis primary cell female adult (55 years)", 
    "treatments": [], 
    "url": "http://www.promocell.com/nc/products/human-primary-cells/fibroblasts/normal-human-dermal-fibroblasts-nhdf/?sword_list%5B%5D=NHDF"
}