{
    "accession": "ENCBS089YMF",
    "age": "unknown",
    "applied_modifications": [
        {
            "category": "insertion",
            "introduced_tags": [
                {
                    "location": "C-terminal",
                    "name": "eGFP"
                },
                {
                    "location": "C-terminal",
                    "name": "FLAG"
                }
            ],
            "modified_site_by_target_id": "sea-2",
            "purpose": "tagging"
        }
    ],
    "biosample_term_id": "UBERON:0000468",
    "biosample_term_name": "whole organism",
    "biosample_type": "whole organisms",
    "characterizations": [],
    "dbxrefs": [],
    "description": "Transgenic C. elegans line, stably expressing a C-terminal GFP-FLAG tag fused to SEA-2",
    "documents": [],
    "donor": "ENCDO705PPA",
    "lab": "Michael Snyder, Stanford",
    "life_stage": "L3 larva",
    "organism": "Caenorhabditis elegans",
    "references": [],
    "sex": "mixed",
    "source": "Michael Snyder",
    "summary": "Caenorhabditis elegans strain OP193 (unc-119(ed3); wgIs193(sea-2::TY1 EGFP FLAG C; unc-119)) mixed sex L3 larva whole organism genetically modified (insertion) using bombardment targeting C. elegans sea-2",
    "treatments": []
}